edist-1.2.2.dist-info/LICENSE.md
edist-1.2.2.dist-info/RECORD
edist-1.2.2.dist-info/top_level.txt
edist-1.2.2.dist-info/WHEEL
edist-1.2.2.dist-info/METADATA
edist/multiprocess.py
edist/seted.cpython-36m-x86_64-linux-gnu.so
edist/bedl.py
edist/tree_utils.py
edist/uted.cpython-36m-x86_64-linux-gnu.so
edist/aed.py
edist/sed.cpython-36m-x86_64-linux-gnu.so
edist/alignment.py
edist/edits.py
edist/ted.cpython-36m-x86_64-linux-gnu.so
edist/dtw.cpython-36m-x86_64-linux-gnu.so
edist/adp.cpython-36m-x86_64-linux-gnu.so
edist/tree_edits.py
