Metadata-Version: 2.1
Name: edist
Version: 1.2.2
Summary: Edit distance implementations in cython
Home-page: https://gitlab.ub.uni-bielefeld.de/bpaassen/python-edit-distances
Author: Benjamin Paassen
Author-email: bpaassen@techfak.uni-bielefeld.de
License: UNKNOWN
Keywords: levenshtein-distance dynamic-time-warping sequence-edit-distance sequence-alignment tree-edit-distance algebraic-dynamic-programming
Platform: UNKNOWN
Classifier: Programming Language :: Python :: 3
Classifier: License :: OSI Approved :: GNU General Public License v3 (GPLv3)
Classifier: Operating System :: OS Independent
License-File: LICENSE.md
Requires-Dist: numpy
Requires-Dist: scikit-learn
Requires-Dist: scipy
Requires-Dist: proto-dist-ml
